[
  {
    "region_name":"Sumatra",
    "status":"success",
    "rmse_all_horizon":66.0002746582,
    "mae_all_horizon":32.2373046875,
    "r2_all_horizon":0.9390832186,
    "mape_all_horizon_pct":25.6192989349,
    "train_rows":36792,
    "val_rows":7884,
    "test_rows":7884,
    "artifact_dir":"C:\\Users\\rohman\\AI-Model\\artifacts_xgboost_representative_points(Gen0.8)\\Sumatra"
  },
  {
    "region_name":"Jawa",
    "status":"success",
    "rmse_all_horizon":61.4913825989,
    "mae_all_horizon":29.9059963226,
    "r2_all_horizon":0.9468046427,
    "mape_all_horizon_pct":23.5025501251,
    "train_rows":36792,
    "val_rows":7884,
    "test_rows":7884,
    "artifact_dir":"C:\\Users\\rohman\\AI-Model\\artifacts_xgboost_representative_points(Gen0.8)\\Jawa"
  },
  {
    "region_name":"Kalimantan",
    "status":"success",
    "rmse_all_horizon":57.4355926514,
    "mae_all_horizon":28.3756866455,
    "r2_all_horizon":0.9520689249,
    "mape_all_horizon_pct":22.00522995,
    "train_rows":36792,
    "val_rows":7884,
    "test_rows":7884,
    "artifact_dir":"C:\\Users\\rohman\\AI-Model\\artifacts_xgboost_representative_points(Gen0.8)\\Kalimantan"
  },
  {
    "region_name":"Sulawesi",
    "status":"success",
    "rmse_all_horizon":59.3227806091,
    "mae_all_horizon":28.6524391174,
    "r2_all_horizon":0.9527007341,
    "mape_all_horizon_pct":21.2415237427,
    "train_rows":36792,
    "val_rows":7884,
    "test_rows":7884,
    "artifact_dir":"C:\\Users\\rohman\\AI-Model\\artifacts_xgboost_representative_points(Gen0.8)\\Sulawesi"
  },
  {
    "region_name":"Nusa Tenggara",
    "status":"success",
    "rmse_all_horizon":56.4285583496,
    "mae_all_horizon":25.9448852539,
    "r2_all_horizon":0.9648758769,
    "mape_all_horizon_pct":16.5090694427,
    "train_rows":36792,
    "val_rows":7884,
    "test_rows":7884,
    "artifact_dir":"C:\\Users\\rohman\\AI-Model\\artifacts_xgboost_representative_points(Gen0.8)\\Nusa_Tenggara"
  },
  {
    "region_name":"Maluku",
    "status":"success",
    "rmse_all_horizon":77.1347808838,
    "mae_all_horizon":37.7861709595,
    "r2_all_horizon":0.9191419482,
    "mape_all_horizon_pct":30.6815261841,
    "train_rows":36792,
    "val_rows":7884,
    "test_rows":7884,
    "artifact_dir":"C:\\Users\\rohman\\AI-Model\\artifacts_xgboost_representative_points(Gen0.8)\\Maluku"
  },
  {
    "region_name":"Papua",
    "status":"success",
    "rmse_all_horizon":48.6004447937,
    "mae_all_horizon":24.1977577209,
    "r2_all_horizon":0.9596124887,
    "mape_all_horizon_pct":18.5216598511,
    "train_rows":36792,
    "val_rows":7884,
    "test_rows":7884,
    "artifact_dir":"C:\\Users\\rohman\\AI-Model\\artifacts_xgboost_representative_points(Gen0.8)\\Papua"
  }
]